claws/__init__.py
claws/aws_utils.py
claws-0.0.22.dist-info/licenses/LICENSE.md
claws-0.0.22.dist-info/METADATA
claws-0.0.22.dist-info/WHEEL
claws-0.0.22.dist-info/top_level.txt
claws-0.0.22.dist-info/RECORD
