Metadata-Version: 2.4
Name: claws
Version: 0.0.22
Summary: The Crossref Labs AWS tooling system.
Home-page: https://gitlab.com/crossref/labs/distrunner
Author: Martin Paul Eve
Author-email: meve@crossref.org
Maintainer-email: Martin Paul Eve <meve@crossref.org>
License: Copyright &copy; 2023 Crossref
Project-URL: homepage, https://labs.crossref.org
Project-URL: documentation, https://labs.crossref.org
Project-URL: repository, https://gitlab.com/crossref/labs/claws
Project-URL: changelog, https://gitlab.com/crossref/labs/claws/-/blob/main/CHANGELOG.md
Keywords: distributed computing
Classifier: Development Status :: 4 - Beta
Classifier: Programming Language :: Python
Requires-Python: >=3.8
License-File: LICENSE.md
Requires-Dist: botocore>=1.33
Requires-Dist: boto3>=1.33
Requires-Dist: aiohttp==3.8.4
Requires-Dist: yarl==1.8.2
Requires-Dist: moto==4.1.6
Requires-Dist: smart-open==6.3.0
Dynamic: license-file
